{
    "root": {
        "comentario": "",
        "xpath": "//section[@id='oportunidades']//a"
    },
    "titulo": {
        "posclick": "",
        "comentario": "",
        "xpath": "//*[@aria-label='Título da vaga']",
        "processadores": [
            {
                "nome": "padraoTitulo",
                "tipo": "",
                "de": "",
                "para": ""
            }
        ]
    },
    "descricao": {
        "posclick": true,
        "comentario": "",
        "xpath": "//h2[contains(text(),'Descrição e Atividades')]/following-sibling::div[1]",
        "processadores": [
            {
                "nome": "padraoDescricao",
                "tipo": "",
                "de": "",
                "para": ""
            }
        ]
    },
    "cidade": {
        "posclick": "",
        "comentario": "",
        "xpath": "//*[@aria-label='Cidade e Estado da vaga']",
        "processadores": [
            {
                "nome": "",
                "tipo": "SplitFirst",
                "de": "-",
                "para": ""
            },
            {
                "nome": "",
                "tipo": "",
                "de": "",
                "para": ""
            },
            {
                "nome": "",
                "tipo": "",
                "de": "",
                "para": ""
            }
        ]
    },
    "estado": {
        "posclick": "",
        "comentario": "",
        "xpath": "//*[@aria-label='Cidade e Estado da vaga']",
        "processadores": [
            {
                "nome": "",
                "tipo": "RegexMatch",
                "de": "-.+",
                "para": ""
            },
            {
                "nome": "",
                "tipo": "Replace",
                "de": "-",
                "para": ""
            }
        ]
    },
    "url_detalhe": {
        "tipo": "href",
        "comentario": "",
        "xpath": "//section[@id='oportunidades']//a"
    },
    "salario": {
        "posclick": "",
        "comentario": "",
        "xpath": "",
        "processadores": [
            {
                "nome": "",
                "tipo": "",
                "de": "",
                "para": ""
            },
            {
                "nome": "",
                "tipo": "",
                "de": "",
                "para": ""
            }
        ]
    },
    "paginacao": {
        "tipo": "",
        "comentario": "Empresa não utiliza paginação",
        "parametro": "",
        "rota_principal": "",
        "script": ""
    },
    "total_vagas": {
        "posclick": "",
        "comentario": "",
        "xpath": "",
        "processadores": [
            {
                "nome": "",
                "tipo": "",
                "de": "",
                "para": ""
            },
            {
                "nome": "",
                "tipo": "",
                "de": "",
                "para": ""
            }
        ]
    },
    "total_vagas_site": {
        "posclick": "",
        "comentario": "",
        "xpath": "",
        "processadores": [
            {
                "nome": "",
                "tipo": "",
                "de": "",
                "para": ""
            },
            {
                "nome": "",
                "tipo": "",
                "de": "",
                "para": ""
            }
        ]
    },
    "total_anuncios_site": {
        "posclick": "",
        "comentario": "",
        "xpath": "",
        "processadores": [
            {
                "nome": "",
                "tipo": "",
                "de": "",
                "para": ""
            },
            {
                "nome": "",
                "tipo": "",
                "de": "",
                "para": ""
            }
        ]
    }
}